[
  {
    "companyId": null,
    "regNumber": "320121000128894",
    "regStatus": "存续",
    "creditCode": "9132011567903066XG",
    "estiblishTime": 1224777600000,
    "regCapital": "501万人民币",
    "companyType": 1,
    "name": "南京泽冠制衣有限公司",
    "id": "2349566267",
    "orgNumber": "67903066X",
    "type": 1,
    "base": "江苏",
    "legalPersonName": "季玮",
    "staffNumRange": null,
    "fromTime": null,
    "bondName": null,
    "isMicroEnt": null,
    "usedBondName": null,
    "percentileScore": null,
    "regInstitute": null,
    "regLocation": null,
    "industry": null,
    "approvedTime": null,
    "socialStaffNum": null,
    "tags": null,
    "taxNumber": null,
    "businessScope": null,
    "property3": null,
    "alias": null,
    "updateTimes": null,
    "bondType": null,
    "toTime": null,
    "actualCapital": null,
    "companyOrgType": null,
    "bondNum": null,
    "regCapitalCurrency": null,
    "actualCapitalCurrency": null,
    "revokeDate": null,
    "revokeReason": null,
    "cancelDate": null,
    "cancelReason": null,
    "city": null,
    "district": null,
    "historyNames": null
  },
  {
    "companyId": null,
    "regNumber": "",
    "regStatus": "在业",
    "creditCode": "91320115MA20JMLN6A",
    "estiblishTime": 1575561600000,
    "regCapital": "100万人民币",
    "companyType": 1,
    "name": "南京泽冠尚商贸有限公司",
    "id": "3395010124",
    "orgNumber": "MA20JMLN6",
    "type": 1,
    "base": "江苏",
    "legalPersonName": "王泽斌",
    "staffNumRange": null,
    "fromTime": null,
    "bondName": null,
    "isMicroEnt": null,
    "usedBondName": null,
    "percentileScore": null,
    "regInstitute": null,
    "regLocation": null,
    "industry": null,
    "approvedTime": null,
    "socialStaffNum": null,
    "tags": null,
    "taxNumber": null,
    "businessScope": null,
    "property3": null,
    "alias": null,
    "updateTimes": null,
    "bondType": null,
    "toTime": null,
    "actualCapital": null,
    "companyOrgType": null,
    "bondNum": null,
    "regCapitalCurrency": null,
    "actualCapitalCurrency": null,
    "revokeDate": null,
    "revokeReason": null,
    "cancelDate": null,
    "cancelReason": null,
    "city": null,
    "district": null,
    "historyNames": null
  },
  {
    "companyId": null,
    "regNumber": "320106000435886",
    "regStatus": "在业",
    "creditCode": "91320106MA1R8AW324",
    "estiblishTime": 1506441600000,
    "regCapital": "50万人民币",
    "companyType": 1,
    "name": "南京泽冠教育咨询有限公司",
    "id": "3124713190",
    "orgNumber": "MA1R8AW32",
    "type": 1,
    "base": "江苏",
    "legalPersonName": "陆肖凝",
    "staffNumRange": null,
    "fromTime": null,
    "bondName": null,
    "isMicroEnt": null,
    "usedBondName": null,
    "percentileScore": null,
    "regInstitute": null,
    "regLocation": null,
    "industry": null,
    "approvedTime": null,
    "socialStaffNum": null,
    "tags": null,
    "taxNumber": null,
    "businessScope": null,
    "property3": null,
    "alias": null,
    "updateTimes": null,
    "bondType": null,
    "toTime": null,
    "actualCapital": null,
    "companyOrgType": null,
    "bondNum": null,
    "regCapitalCurrency": null,
    "actualCapitalCurrency": null,
    "revokeDate": null,
    "revokeReason": null,
    "cancelDate": null,
    "cancelReason": null,
    "city": null,
    "district": null,
    "historyNames": null
  },
  {
    "companyId": null,
    "regNumber": "320121000504970",
    "regStatus": "在业",
    "creditCode": "91320115MA1MP3J8XC",
    "estiblishTime": 1467561600000,
    "regCapital": "200万人民币",
    "companyType": 1,
    "name": "南京冠泽电子商务有限公司",
    "id": "2964246363",
    "orgNumber": "MA1MP3J8X",
    "type": 1,
    "base": "江苏",
    "legalPersonName": "夏冬",
    "staffNumRange": null,
    "fromTime": null,
    "bondName": null,
    "isMicroEnt": null,
    "usedBondName": null,
    "percentileScore": null,
    "regInstitute": null,
    "regLocation": null,
    "industry": null,
    "approvedTime": null,
    "socialStaffNum": null,
    "tags": null,
    "taxNumber": null,
    "businessScope": null,
    "property3": null,
    "alias": null,
    "updateTimes": null,
    "bondType": null,
    "toTime": null,
    "actualCapital": null,
    "companyOrgType": null,
    "bondNum": null,
    "regCapitalCurrency": null,
    "actualCapitalCurrency": null,
    "revokeDate": null,
    "revokeReason": null,
    "cancelDate": null,
    "cancelReason": null,
    "city": null,
    "district": null,
    "historyNames": null
  },
  {
    "companyId": null,
    "regNumber": "320103000112131",
    "regStatus": "注销",
    "creditCode": "",
    "estiblishTime": 1179417600000,
    "regCapital": "30万人民币",
    "companyType": 1,
    "name": "南京泽冠贸易有限公司",
    "id": "2350271134",
    "orgNumber": "",
    "type": 1,
    "base": "江苏",
    "legalPersonName": "季玮",
    "staffNumRange": null,
    "fromTime": null,
    "bondName": null,
    "isMicroEnt": null,
    "usedBondName": null,
    "percentileScore": null,
    "regInstitute": null,
    "regLocation": null,
    "industry": null,
    "approvedTime": null,
    "socialStaffNum": null,
    "tags": null,
    "taxNumber": null,
    "businessScope": null,
    "property3": null,
    "alias": null,
    "updateTimes": null,
    "bondType": null,
    "toTime": null,
    "actualCapital": null,
    "companyOrgType": null,
    "bondNum": null,
    "regCapitalCurrency": null,
    "actualCapitalCurrency": null,
    "revokeDate": null,
    "revokeReason": null,
    "cancelDate": null,
    "cancelReason": null,
    "city": null,
    "district": null,
    "historyNames": null
  },
  {
    "companyId": null,
    "regNumber": "320104000369747",
    "regStatus": "注销",
    "creditCode": "91320104MA1R60KE8A",
    "estiblishTime": 1505318400000,
    "regCapital": "200万人民币",
    "companyType": 1,
    "name": "南京泽冠建筑工程有限公司",
    "id": "3095054410",
    "orgNumber": "MA1R60KE8",
    "type": 1,
    "base": "江苏",
    "legalPersonName": "宋体兵",
    "staffNumRange": null,
    "fromTime": null,
    "bondName": null,
    "isMicroEnt": null,
    "usedBondName": null,
    "percentileScore": null,
    "regInstitute": null,
    "regLocation": null,
    "industry": null,
    "approvedTime": null,
    "socialStaffNum": null,
    "tags": null,
    "taxNumber": null,
    "businessScope": null,
    "property3": null,
    "alias": null,
    "updateTimes": null,
    "bondType": null,
    "toTime": null,
    "actualCapital": null,
    "companyOrgType": null,
    "bondNum": null,
    "regCapitalCurrency": null,
    "actualCapitalCurrency": null,
    "revokeDate": null,
    "revokeReason": null,
    "cancelDate": null,
    "cancelReason": null,
    "city": null,
    "district": null,
    "historyNames": null
  },
  {
    "companyId": null,
    "regNumber": "",
    "regStatus": "在业",
    "creditCode": "91320113MA20T4UC97",
    "estiblishTime": 1578585600000,
    "regCapital": "1000万人民币",
    "companyType": 1,
    "name": "江苏泽冠信息科技有限公司",
    "id": "3405434294",
    "orgNumber": "MA20T4UC9",
    "type": 1,
    "base": "江苏",
    "legalPersonName": "王建梅",
    "staffNumRange": null,
    "fromTime": null,
    "bondName": null,
    "isMicroEnt": null,
    "usedBondName": null,
    "percentileScore": null,
    "regInstitute": null,
    "regLocation": null,
    "industry": null,
    "approvedTime": null,
    "socialStaffNum": null,
    "tags": null,
    "taxNumber": null,
    "businessScope": null,
    "property3": null,
    "alias": null,
    "updateTimes": null,
    "bondType": null,
    "toTime": null,
    "actualCapital": null,
    "companyOrgType": null,
    "bondNum": null,
    "regCapitalCurrency": null,
    "actualCapitalCurrency": null,
    "revokeDate": null,
    "revokeReason": null,
    "cancelDate": null,
    "cancelReason": null,
    "city": null,
    "district": null,
    "historyNames": null
  },
  {
    "companyId": null,
    "regNumber": "",
    "regStatus": "在业",
    "creditCode": "91320115MA1X3N2B0X",
    "estiblishTime": 1535299200000,
    "regCapital": "5万人民币",
    "companyType": 1,
    "name": "南京冠泽建筑劳务有限公司",
    "id": "3223344695",
    "orgNumber": "MA1X3N2B0",
    "type": 1,
    "base": "江苏",
    "legalPersonName": "施剑华",
    "staffNumRange": null,
    "fromTime": null,
    "bondName": null,
    "isMicroEnt": null,
    "usedBondName": null,
    "percentileScore": null,
    "regInstitute": null,
    "regLocation": null,
    "industry": null,
    "approvedTime": null,
    "socialStaffNum": null,
    "tags": null,
    "taxNumber": null,
    "businessScope": null,
    "property3": null,
    "alias": null,
    "updateTimes": null,
    "bondType": null,
    "toTime": null,
    "actualCapital": null,
    "companyOrgType": null,
    "bondNum": null,
    "regCapitalCurrency": null,
    "actualCapitalCurrency": null,
    "revokeDate": null,
    "revokeReason": null,
    "cancelDate": null,
    "cancelReason": null,
    "city": null,
    "district": null,
    "historyNames": null
  },
  {
    "companyId": null,
    "regNumber": "",
    "regStatus": "在业",
    "creditCode": "91320115MA1X2YLL88",
    "estiblishTime": 1534780800000,
    "regCapital": "200万人民币",
    "companyType": 1,
    "name": "南京冠泽建材商贸有限公司",
    "id": "3223012318",
    "orgNumber": "MA1X2YLL8",
    "type": 1,
    "base": "江苏",
    "legalPersonName": "施剑华",
    "staffNumRange": null,
    "fromTime": null,
    "bondName": null,
    "isMicroEnt": null,
    "usedBondName": null,
    "percentileScore": null,
    "regInstitute": null,
    "regLocation": null,
    "industry": null,
    "approvedTime": null,
    "socialStaffNum": null,
    "tags": null,
    "taxNumber": null,
    "businessScope": null,
    "property3": null,
    "alias": null,
    "updateTimes": null,
    "bondType": null,
    "toTime": null,
    "actualCapital": null,
    "companyOrgType": null,
    "bondNum": null,
    "regCapitalCurrency": null,
    "actualCapitalCurrency": null,
    "revokeDate": null,
    "revokeReason": null,
    "cancelDate": null,
    "cancelReason": null,
    "city": null,
    "district": null,
    "historyNames": null
  },
  {
    "companyId": null,
    "regNumber": "320114000231752",
    "regStatus": "在业",
    "creditCode": "91320114MA1Q42PGX0",
    "estiblishTime": 1502985600000,
    "regCapital": "200万人民币",
    "companyType": 1,
    "name": "南京冠泽建筑工程有限公司",
    "id": "3089459529",
    "orgNumber": "MA1Q42PGX",
    "type": 1,
    "base": "江苏",
    "legalPersonName": "施剑华",
    "staffNumRange": null,
    "fromTime": null,
    "bondName": null,
    "isMicroEnt": null,
    "usedBondName": null,
    "percentileScore": null,
    "regInstitute": null,
    "regLocation": null,
    "industry": null,
    "approvedTime": null,
    "socialStaffNum": null,
    "tags": null,
    "taxNumber": null,
    "businessScope": null,
    "property3": null,
    "alias": null,
    "updateTimes": null,
    "bondType": null,
    "toTime": null,
    "actualCapital": null,
    "companyOrgType": null,
    "bondNum": null,
    "regCapitalCurrency": null,
    "actualCapitalCurrency": null,
    "revokeDate": null,
    "revokeReason": null,
    "cancelDate": null,
    "cancelReason": null,
    "city": null,
    "district": null,
    "historyNames": null
  },
  {
    "companyId": null,
    "regNumber": "",
    "regStatus": "注销",
    "creditCode": "92320105MA202F141J",
    "estiblishTime": 1568044800000,
    "regCapital": "10万人民币",
    "companyType": 1,
    "name": "南京市建邺区泽翡冠百货经营部",
    "id": "3369686507",
    "orgNumber": "MA202F141",
    "type": 1,
    "base": "江苏",
    "legalPersonName": "张凡",
    "staffNumRange": null,
    "fromTime": null,
    "bondName": null,
    "isMicroEnt": null,
    "usedBondName": null,
    "percentileScore": null,
    "regInstitute": null,
    "regLocation": null,
    "industry": null,
    "approvedTime": null,
    "socialStaffNum": null,
    "tags": null,
    "taxNumber": null,
    "businessScope": null,
    "property3": null,
    "alias": null,
    "updateTimes": null,
    "bondType": null,
    "toTime": null,
    "actualCapital": null,
    "companyOrgType": null,
    "bondNum": null,
    "regCapitalCurrency": null,
    "actualCapitalCurrency": null,
    "revokeDate": null,
    "revokeReason": null,
    "cancelDate": null,
    "cancelReason": null,
    "city": null,
    "district": null,
    "historyNames": null
  },
  {
    "companyId": null,
    "regNumber": "130102000045023",
    "regStatus": "存续",
    "creditCode": "911301020813083997",
    "estiblishTime": 1382457600000,
    "regCapital": "50万人民币",
    "companyType": 1,
    "name": "石家庄泽冠商贸有限公司",
    "id": "322346754",
    "orgNumber": "081308399",
    "type": 1,
    "base": "河北",
    "legalPersonName": "王红霞",
    "staffNumRange": null,
    "fromTime": null,
    "bondName": null,
    "isMicroEnt": null,
    "usedBondName": null,
    "percentileScore": null,
    "regInstitute": null,
    "regLocation": null,
    "industry": null,
    "approvedTime": null,
    "socialStaffNum": null,
    "tags": null,
    "taxNumber": null,
    "businessScope": null,
    "property3": null,
    "alias": null,
    "updateTimes": null,
    "bondType": null,
    "toTime": null,
    "actualCapital": null,
    "companyOrgType": null,
    "bondNum": null,
    "regCapitalCurrency": null,
    "actualCapitalCurrency": null,
    "revokeDate": null,
    "revokeReason": null,
    "cancelDate": null,
    "cancelReason": null,
    "city": null,
    "district": null,
    "historyNames": null
  },
  {
    "companyId": null,
    "regNumber": "",
    "regStatus": "在业",
    "creditCode": "91320829MA236PR81F",
    "estiblishTime": 1605628800000,
    "regCapital": "-",
    "companyType": 1,
    "name": "南京冠福建设工程技术有限公司洪泽分公司",
    "id": "4028699477",
    "orgNumber": "MA236PR81",
    "type": 1,
    "base": "江苏",
    "legalPersonName": "吴侃",
    "staffNumRange": null,
    "fromTime": null,
    "bondName": null,
    "isMicroEnt": null,
    "usedBondName": null,
    "percentileScore": null,
    "regInstitute": null,
    "regLocation": null,
    "industry": null,
    "approvedTime": null,
    "socialStaffNum": null,
    "tags": null,
    "taxNumber": null,
    "businessScope": null,
    "property3": null,
    "alias": null,
    "updateTimes": null,
    "bondType": null,
    "toTime": null,
    "actualCapital": null,
    "companyOrgType": null,
    "bondNum": null,
    "regCapitalCurrency": null,
    "actualCapitalCurrency": null,
    "revokeDate": null,
    "revokeReason": null,
    "cancelDate": null,
    "cancelReason": null,
    "city": null,
    "district": null,
    "historyNames": null
  },
  {
    "companyId": null,
    "regNumber": "320111600661514",
    "regStatus": "在业",
    "creditCode": "",
    "estiblishTime": 1463500800000,
    "regCapital": "99万人民币",
    "companyType": 1,
    "name": "南京市浦口区冠泽轩精菜馆",
    "id": "2886313306",
    "orgNumber": "",
    "type": 1,
    "base": "江苏",
    "legalPersonName": "汪泽浩",
    "staffNumRange": null,
    "fromTime": null,
    "bondName": null,
    "isMicroEnt": null,
    "usedBondName": null,
    "percentileScore": null,
    "regInstitute": null,
    "regLocation": null,
    "industry": null,
    "approvedTime": null,
    "socialStaffNum": null,
    "tags": null,
    "taxNumber": null,
    "businessScope": null,
    "property3": null,
    "alias": null,
    "updateTimes": null,
    "bondType": null,
    "toTime": null,
    "actualCapital": null,
    "companyOrgType": null,
    "bondNum": null,
    "regCapitalCurrency": null,
    "actualCapitalCurrency": null,
    "revokeDate": null,
    "revokeReason": null,
    "cancelDate": null,
    "cancelReason": null,
    "city": null,
    "district": null,
    "historyNames": null
  },
  {
    "companyId": null,
    "regNumber": "",
    "regStatus": "在业",
    "creditCode": "92320116MA20A8JK1U",
    "estiblishTime": 1571932800000,
    "regCapital": "5万人民币",
    "companyType": 1,
    "name": "南京市六合区冠泽五金建材经营部",
    "id": "3381543014",
    "orgNumber": "MA20A8JK1",
    "type": 1,
    "base": "江苏",
    "legalPersonName": "陈亭友",
    "staffNumRange": null,
    "fromTime": null,
    "bondName": null,
    "isMicroEnt": null,
    "usedBondName": null,
    "percentileScore": null,
    "regInstitute": null,
    "regLocation": null,
    "industry": null,
    "approvedTime": null,
    "socialStaffNum": null,
    "tags": null,
    "taxNumber": null,
    "businessScope": null,
    "property3": null,
    "alias": null,
    "updateTimes": null,
    "bondType": null,
    "toTime": null,
    "actualCapital": null,
    "companyOrgType": null,
    "bondNum": null,
    "regCapitalCurrency": null,
    "actualCapitalCurrency": null,
    "revokeDate": null,
    "revokeReason": null,
    "cancelDate": null,
    "cancelReason": null,
    "city": null,
    "district": null,
    "historyNames": null
  },
  {
    "companyId": null,
    "regNumber": "320102600387674",
    "regStatus": "在业",
    "creditCode": "92320102MA1QQMXB44",
    "estiblishTime": 1429372800000,
    "regCapital": "2万人民币",
    "companyType": 1,
    "name": "南京市玄武区冠灵泽电子经营部",
    "id": "2883430191",
    "orgNumber": "MA1QQMXB4",
    "type": 1,
    "base": "江苏",
    "legalPersonName": "朱冠术",
    "staffNumRange": null,
    "fromTime": null,
    "bondName": null,
    "isMicroEnt": null,
    "usedBondName": null,
    "percentileScore": null,
    "regInstitute": null,
    "regLocation": null,
    "industry": null,
    "approvedTime": null,
    "socialStaffNum": null,
    "tags": null,
    "taxNumber": null,
    "businessScope": null,
    "property3": null,
    "alias": null,
    "updateTimes": null,
    "bondType": null,
    "toTime": null,
    "actualCapital": null,
    "companyOrgType": null,
    "bondNum": null,
    "regCapitalCurrency": null,
    "actualCapitalCurrency": null,
    "revokeDate": null,
    "revokeReason": null,
    "cancelDate": null,
    "cancelReason": null,
    "city": null,
    "district": null,
    "historyNames": null
  },
  {
    "companyId": null,
    "regNumber": "320102600433992",
    "regStatus": "在业",
    "creditCode": "92320102MA1PY1JB0L",
    "estiblishTime": 1472745600000,
    "regCapital": "1万人民币",
    "companyType": 1,
    "name": "南京市玄武区泽至冠商贸中心",
    "id": "2625325111",
    "orgNumber": "MA1PY1JB0",
    "type": 1,
    "base": "江苏",
    "legalPersonName": "刘今朝",
    "staffNumRange": null,
    "fromTime": null,
    "bondName": null,
    "isMicroEnt": null,
    "usedBondName": null,
    "percentileScore": null,
    "regInstitute": null,
    "regLocation": null,
    "industry": null,
    "approvedTime": null,
    "socialStaffNum": null,
    "tags": null,
    "taxNumber": null,
    "businessScope": null,
    "property3": null,
    "alias": null,
    "updateTimes": null,
    "bondType": null,
    "toTime": null,
    "actualCapital": null,
    "companyOrgType": null,
    "bondNum": null,
    "regCapitalCurrency": null,
    "actualCapitalCurrency": null,
    "revokeDate": null,
    "revokeReason": null,
    "cancelDate": null,
    "cancelReason": null,
    "city": null,
    "district": null,
    "historyNames": null
  },
  {
    "companyId": null,
    "regNumber": "320113000031011",
    "regStatus": "注销",
    "creditCode": "",
    "estiblishTime": 1137081600000,
    "regCapital": "158万人民币",
    "companyType": 1,
    "name": "南京冠泽装饰材料有限公司",
    "id": "2353705275",
    "orgNumber": "",
    "type": 1,
    "base": "江苏",
    "legalPersonName": "谢智华",
    "staffNumRange": null,
    "fromTime": null,
    "bondName": null,
    "isMicroEnt": null,
    "usedBondName": null,
    "percentileScore": null,
    "regInstitute": null,
    "regLocation": null,
    "industry": null,
    "approvedTime": null,
    "socialStaffNum": null,
    "tags": null,
    "taxNumber": null,
    "businessScope": null,
    "property3": null,
    "alias": null,
    "updateTimes": null,
    "bondType": null,
    "toTime": null,
    "actualCapital": null,
    "companyOrgType": null,
    "bondNum": null,
    "regCapitalCurrency": null,
    "actualCapitalCurrency": null,
    "revokeDate": null,
    "revokeReason": null,
    "cancelDate": null,
    "cancelReason": null,
    "city": null,
    "district": null,
    "historyNames": null
  },
  {
    "companyId": null,
    "regNumber": "3201022306845",
    "regStatus": "吊销，未注销",
    "creditCode": "",
    "estiblishTime": 1144598400000,
    "regCapital": "3万",
    "companyType": 1,
    "name": "南京冠泽漫画艺术有限公司",
    "id": "2421376282",
    "orgNumber": "",
    "type": 1,
    "base": "江苏",
    "legalPersonName": "黄永道",
    "staffNumRange": null,
    "fromTime": null,
    "bondName": null,
    "isMicroEnt": null,
    "usedBondName": null,
    "percentileScore": null,
    "regInstitute": null,
    "regLocation": null,
    "industry": null,
    "approvedTime": null,
    "socialStaffNum": null,
    "tags": null,
    "taxNumber": null,
    "businessScope": null,
    "property3": null,
    "alias": null,
    "updateTimes": null,
    "bondType": null,
    "toTime": null,
    "actualCapital": null,
    "companyOrgType": null,
    "bondNum": null,
    "regCapitalCurrency": null,
    "actualCapitalCurrency": null,
    "revokeDate": null,
    "revokeReason": null,
    "cancelDate": null,
    "cancelReason": null,
    "city": null,
    "district": null,
    "historyNames": null
  },
  {
    "companyId": null,
    "regNumber": "320121000527695",
    "regStatus": "注销",
    "creditCode": "91320115MA1MTU658Q",
    "estiblishTime": 1473004800000,
    "regCapital": "2万人民币",
    "companyType": 1,
    "name": "南京冠茗泽电子贸易有限公司",
    "id": "2372710377",
    "orgNumber": "MA1MTU658",
    "type": 1,
    "base": "江苏",
    "legalPersonName": "高广孝",
    "staffNumRange": null,
    "fromTime": null,
    "bondName": null,
    "isMicroEnt": null,
    "usedBondName": null,
    "percentileScore": null,
    "regInstitute": null,
    "regLocation": null,
    "industry": null,
    "approvedTime": null,
    "socialStaffNum": null,
    "tags": null,
    "taxNumber": null,
    "businessScope": null,
    "property3": null,
    "alias": null,
    "updateTimes": null,
    "bondType": null,
    "toTime": null,
    "actualCapital": null,
    "companyOrgType": null,
    "bondNum": null,
    "regCapitalCurrency": null,
    "actualCapitalCurrency": null,
    "revokeDate": null,
    "revokeReason": null,
    "cancelDate": null,
    "cancelReason": null,
    "city": null,
    "district": null,
    "historyNames": null
  }
]